uxarray/__init__.py
uxarray/constants.py
uxarray/formatting_html.py
uxarray/conventions/__init__.py
uxarray/conventions/descriptors.py
uxarray/conventions/ugrid.py
uxarray/core/__init__.py
uxarray/core/accessors.py
uxarray/core/aggregation.py
uxarray/core/api.py
uxarray/core/dataarray.py
uxarray/core/dataset.py
uxarray/core/gradient.py
uxarray/core/utils.py
uxarray/core/zonal.py
uxarray/cross_sections/__init__.py
uxarray/cross_sections/dataarray_accessor.py
uxarray/cross_sections/grid_accessor.py
uxarray/cross_sections/sample.py
uxarray/grid/__init__.py
uxarray/grid/arcs.py
uxarray/grid/area.py
uxarray/grid/bounds.py
uxarray/grid/connectivity.py
uxarray/grid/coordinates.py
uxarray/grid/dual.py
uxarray/grid/geometry.py
uxarray/grid/grid.py
uxarray/grid/integrate.py
uxarray/grid/intersections.py
uxarray/grid/neighbors.py
uxarray/grid/point_in_face.py
uxarray/grid/slice.py
uxarray/grid/utils.py
uxarray/grid/validation.py
uxarray/io/__init__.py
uxarray/io/_delaunay.py
uxarray/io/_esmf.py
uxarray/io/_exodus.py
uxarray/io/_fesom2.py
uxarray/io/_geopandas.py
uxarray/io/_geos.py
uxarray/io/_healpix.py
uxarray/io/_icon.py
uxarray/io/_mpas.py
uxarray/io/_scrip.py
uxarray/io/_structured.py
uxarray/io/_topology.py
uxarray/io/_ugrid.py
uxarray/io/_vertices.py
uxarray/io/_voronoi.py
uxarray/io/utils.py
uxarray/plot/__init__.py
uxarray/plot/accessor.py
uxarray/plot/constants.py
uxarray/plot/matplotlib.py
uxarray/plot/utils.py
uxarray/remap/__init__.py
uxarray/remap/accessor.py
uxarray/remap/bilinear.py
uxarray/remap/inverse_distance_weighted.py
uxarray/remap/nearest_neighbor.py
uxarray/remap/utils.py
uxarray/subset/__init__.py
uxarray/subset/dataarray_accessor.py
uxarray/subset/grid_accessor.py
uxarray/utils/__init__.py
uxarray/utils/computing.py
uxarray-2025.12.0.dist-info/licenses/LICENSE
uxarray-2025.12.0.dist-info/METADATA
uxarray-2025.12.0.dist-info/WHEEL
uxarray-2025.12.0.dist-info/top_level.txt
uxarray-2025.12.0.dist-info/RECORD
