Metadata-Version: 2.4
Name: uxarray
Version: 2025.12.0
Summary: Xarray extension for unstructured climate and global weather data analysis and visualization.
License:                                  Apache License
Project-URL: Documentation, https://uxarray.readthedocs.io/
Project-URL: Source, https://github.com/UXARRAY/uxarray
Project-URL: Tracker, https://github.com/UXARRAY/uxarray/issues
Keywords: unstructured grids,xarray,ugrid,mpas,exodus,scrip,fesom,icon,esmf
Classifier: Operating System :: OS Independent
Classifier: Intended Audience :: Science/Research
Classifier: Topic :: Scientific/Engineering
Classifier: Programming Language :: Python
Classifier: Programming Language :: Python :: 3
Classifier: Programming Language :: Python :: 3.10
Classifier: Programming Language :: Python :: 3.11
Classifier: Programming Language :: Python :: 3.12
Classifier: Programming Language :: Python :: 3.13
Requires-Python: >=3.10
License-File: LICENSE
Requires-Dist: antimeridian
Requires-Dist: cartopy
Requires-Dist: dask[dataframe]
Requires-Dist: datashader
Requires-Dist: geoviews
Requires-Dist: holoviews
Requires-Dist: matplotlib
Requires-Dist: matplotlib-inline
Requires-Dist: netcdf4
Requires-Dist: numba
Requires-Dist: numpy<2.3
Requires-Dist: pandas
Requires-Dist: pyarrow
Requires-Dist: requests
Requires-Dist: scikit-learn
Requires-Dist: scipy
Requires-Dist: shapely
Requires-Dist: spatialpandas
Requires-Dist: geopandas
Requires-Dist: xarray
Requires-Dist: hvplot
Requires-Dist: healpix
Requires-Dist: polars
Requires-Dist: pyproj
Provides-Extra: complete
Requires-Dist: uxarray[dev]; extra == "complete"
Provides-Extra: dev
Requires-Dist: pathlib; extra == "dev"
Requires-Dist: pre_commit; extra == "dev"
Requires-Dist: pytest; extra == "dev"
Requires-Dist: pytest-cov; extra == "dev"
Requires-Dist: ruff; extra == "dev"
Requires-Dist: asv; extra == "dev"
Dynamic: license-file
